montu/__cycle_0.py
montu/__cycle_1.py
montu/__cycle_2.py
montu/__cycle_3.py
montu/__init__.py
montu/heka.py
montu/observer.py
montu/sebau.py
montu/stars.py
montu/time.py
montu/util.py
montu/version.py
montu/data/bright_stars.csv
montu/data/corrections_dt.dat
montu/data/earth_assoc_itrf93.tf
montu/data/frame.tk
montu/data/montu-python-logo-complete.png
montu/data/montu_stellar_catalogue_v37.csv
montu/data/montu_stellar_catalogue_v37_visible.csv
montu/data/montu_stellar_catalogue_v38.csv
montu/data/naif0012.tls
montu/data/pck00011.tpc
montu/data/planets-jpl.csv
montu/data/stars.csv
montu/legacy/__cycle_0.py
montu/legacy/__cycle_1.py
montu/legacy/__cycle_2.py
montu/legacy/__cycle_3.py
montu/legacy/__init__.py
montu/legacy/heka.py
montu/legacy/observer.py
montu/legacy/planets.py
montu/legacy/stars.py
montu/legacy/time.py
montu/legacy/util.py
montu/legacy/version.py
montu-0.9.10.dist-info/licenses/LICENSE
montu-0.9.10.dist-info/METADATA
montu-0.9.10.dist-info/WHEEL
montu-0.9.10.dist-info/entry_points.txt
montu-0.9.10.dist-info/top_level.txt
montu-0.9.10.dist-info/RECORD
