Metadata-Version: 2.4
Name: montu
Version: 0.9.10
Summary: Montu Python: astronomical ephemerides for the ancient world
Home-page: https://pypi.org/project/montu
Author: Jorge Zuluaga, Tito Vivas, Juanita Agudelo
Author-email: jorge.zuluaga@gmail.com
License: MIT
Keywords: astronomy egypt history
Classifier: Programming Language :: Python :: 3
Classifier: License :: OSI Approved :: MIT License
Classifier: Operating System :: OS Independent
License-File: LICENSE
Requires-Dist: scipy
Requires-Dist: ipython
Requires-Dist: matplotlib
Requires-Dist: tqdm
Requires-Dist: numpy
Requires-Dist: ephem
Requires-Dist: pymeeus
Requires-Dist: regex
Requires-Dist: pandas
Requires-Dist: tabulate
Requires-Dist: numpy
Requires-Dist: spiceypy
Requires-Dist: pyplanets
Requires-Dist: requests
Requires-Dist: dash
Requires-Dist: dash_bootstrap_components
Dynamic: author
Dynamic: author-email
Dynamic: classifier
Dynamic: description
Dynamic: description-content-type
Dynamic: home-page
Dynamic: keywords
Dynamic: license
Dynamic: license-file
Dynamic: requires-dist
Dynamic: summary
